setup.py
RotCaesarCipher/__init__.py
RotCaesarCipher/modelo.py
rotcaesarcipher.egg-info/PKG-INFO
rotcaesarcipher.egg-info/SOURCES.txt
rotcaesarcipher.egg-info/dependency_links.txt
rotcaesarcipher.egg-info/not-zip-safe
rotcaesarcipher.egg-info/top_level.txt