Metadata-Version: 1.0
Name: rotcaesarcipher
Version: 0.5
Summary: ROT-n encrypt and decrypt
Home-page: https://github.com/andersongomes001/CaesarCipher
Author: Anderson Gomes
Author-email: comprasgomes@hotmail.com
License: GNU GPL v3
Platform: UNKNOWN
